pylint_guidelines_checker.py
azure_pylint_guidelines_checker-0.0.8.dist-info/METADATA
azure_pylint_guidelines_checker-0.0.8.dist-info/WHEEL
azure_pylint_guidelines_checker-0.0.8.dist-info/top_level.txt
azure_pylint_guidelines_checker-0.0.8.dist-info/RECORD
