Metadata-Version: 2.1
Name: azure-pylint-guidelines-checker
Version: 0.0.8
Summary: A pylint plugin which enforces azure sdk guidelines.
Home-page: http://github.com/Azure/azure-sdk-for-python
Author: Microsoft Corporation
Author-email: azpysdkhelp@microsoft.com
License: MIT License
Platform: UNKNOWN
Requires-Python: >=3.7
